LICENSE
MANIFEST.in
README.md
requirements-dev.txt
requirements.txt
setup.py
pyapputil/__init__.py
pyapputil/appconfig.py
pyapputil/appframework.py
pyapputil/argutil.py
pyapputil/exceptutil.py
pyapputil/logutil.py
pyapputil/netutil.py
pyapputil/shellutil.py
pyapputil/threadutil.py
pyapputil/typeutil.py
pyapputil/util.py
pyapputil.egg-info/PKG-INFO
pyapputil.egg-info/SOURCES.txt
pyapputil.egg-info/dependency_links.txt
pyapputil.egg-info/requires.txt
pyapputil.egg-info/top_level.txt