Metadata-Version: 2.1
Name: pyapputil
Version: 1.1.8
Summary: Tools for building CLI applications
Home-page: https://github.com/cseelye/pyapputil
Author: Carl Seelye
Author-email: cseelye@gmail.com
License: MIT
Keywords: cli arguments configuration logging signals threads time
Platform: UNKNOWN
License-File: LICENSE
